{
    "fluentMethods": true,
    "clientRootFolder": "",
    "relationships": [
        {
            "relationshipName": "userAddress",
            "otherEntityName": "user",
            "relationshipType": "one-to-one",
            "otherEntityField": "login",
            "ownerSide": true,
            "useJPADerivedIdentifier": false,
            "otherEntityRelationshipName": "address"
        }
    ],
    "fields": [
        {
            "fieldName": "streetName",
            "fieldType": "String"
        },
        {
            "fieldName": "complexName",
            "fieldType": "String"
        },
        {
            "fieldName": "city",
            "fieldType": "String"
        },
        {
            "fieldName": "postalCode",
            "fieldType": "Integer"
        },
        {
            "fieldName": "province",
            "fieldType": "String"
        }
    ],
    "changelogDate": "20200219153322",
    "dto": "mapstruct",
    "searchEngine": false,
    "service": "serviceImpl",
    "entityTableName": "address",
    "databaseType": "sql",
    "readOnly": false,
    "jpaMetamodelFiltering": false,
    "pagination": "infinite-scroll"
}
